m3u8downloader/__init__.py
m3u8downloader/config.py
m3u8downloader/configlogger.py
m3u8downloader/logger.conf
m3u8downloader/main.py
m3u8downloader/test_main.py
m3u8downloader/test_signal_handler.py
m3u8downloader-0.11.1.dist-info/METADATA
m3u8downloader-0.11.1.dist-info/WHEEL
m3u8downloader-0.11.1.dist-info/entry_points.txt
m3u8downloader-0.11.1.dist-info/top_level.txt
m3u8downloader-0.11.1.dist-info/RECORD
