Metadata-Version: 2.1
Name: m3u8downloader
Version: 0.11.1
Summary: a cli program to download video at m3u8 url
Home-page: https://pypi.org/project/m3u8downloader/
Author: Yuanle Song
Author-email: sylecn@gmail.com
Maintainer: Yuanle Song
Maintainer-email: sylecn@gmail.com
License: GPLv2+
Classifier: Development Status :: 4 - Beta
Classifier: License :: OSI Approved :: GNU General Public License (GPL)
Classifier: License :: OSI Approved :: GNU General Public License v2 or later (GPLv2+)
Classifier: Programming Language :: Python :: 3.5
Requires-Dist: requests>=2.25.1
Requires-Dist: wells>=1.5.0
